tests/__init__.py
tests/conftest.py
tests/test_elastic.py
tests/test_mongo.py
tests/test_mysql.py
tests/test_redis.py
tests/test_sqlite.py
tests/test_utils.py
zwdb/__init__.py
zwdb/__version__.py
zwdb/records.py
zwdb/utils.py
zwdb/zwdbase.py
zwdb/zwelastic.py
zwdb/zwmongo.py
zwdb/zwmysql.py
zwdb/zwredis.py
zwdb/zwsqlite.py
zwdb-0.0.52.dist-info/LICENSE
zwdb-0.0.52.dist-info/METADATA
zwdb-0.0.52.dist-info/WHEEL
zwdb-0.0.52.dist-info/top_level.txt
zwdb-0.0.52.dist-info/RECORD
