Metadata-Version: 2.1
Name: zwdb
Version: 0.0.52
Summary: Personal Database Wrapper.
Home-page: https://github.com/njzhaowei
Author: Zhao Wei
Author-email: yewberry@163.com
License: Apache 2.0
Platform: all
Classifier: Programming Language :: Python :: 3
Classifier: License :: OSI Approved :: Apache Software License
Classifier: Operating System :: OS Independent
Requires-Python: >=3.6
License-File: LICENSE
Requires-Dist: mysql-connector-python
Requires-Dist: pymongo
Requires-Dist: redis
Requires-Dist: elasticsearch
